simplemoduleypw2234test22345/__init__.py
simplemoduleypw2234test22345/add.py
simplemoduleypw2234test22345/subtract.py
simplemoduleypw2234test22345/extras/__init__.py
simplemoduleypw2234test22345/extras/divide.py
simplemoduleypw2234test22345/extras/multiply.py
simplemoduleypw2234test22345-0.0.7.dist-info/METADATA
simplemoduleypw2234test22345-0.0.7.dist-info/WHEEL
simplemoduleypw2234test22345-0.0.7.dist-info/top_level.txt
simplemoduleypw2234test22345-0.0.7.dist-info/RECORD
