Metadata-Version: 2.1
Name: simplemoduleypw2234test22345
Version: 0.0.7
Summary: My first Python package
Home-page: UNKNOWN
Author: Yunping Wang
Author-email: <wangj6@carleton.edu>
License: UNKNOWN
Keywords: python,first package
Platform: UNKNOWN
Classifier: Development Status :: 3 - Alpha
Classifier: Intended Audience :: Education
Classifier: Programming Language :: Python :: 2
Classifier: Programming Language :: Python :: 3
Classifier: Operating System :: MacOS :: MacOS X
Classifier: Operating System :: Microsoft :: Windows
